LICENSE.txt
MANIFEST.in
README.rst
setup.py
django_search_views.egg-info/PKG-INFO
django_search_views.egg-info/SOURCES.txt
django_search_views.egg-info/dependency_links.txt
django_search_views.egg-info/requires.txt
django_search_views.egg-info/top_level.txt
search_views/__init__.py
search_views/filters.py
search_views/search.py
search_views/views.py