Metadata-Version: 1.1
Name: django-search-views
Version: 0.3.1
Summary: Search List class-based views for Django
Home-page: https://github.com/inmagik/django-search-views
Author: Mauro Bianchi
Author-email: bianchimro@gmail.com
License: MIT
Platform: UNKNOWN
Classifier: Development Status :: 3 - Alpha
Classifier: Environment :: Web Environment
Classifier: Framework :: Django
Classifier: Intended Audience :: Developers
Classifier: Programming Language :: Python
